LICENSE
MANIFEST.in
setup.cfg
setup.py
lib/__init__.py
lib/converters.py
lib/base/__init__.py
lib/base/address.py
lib/base/allocator.py
lib/base/declaration.py
lib/base/memory_region.py
lib/base/numeric_region.py
lib/base/paranoia_agent.py
lib/base/pointer.py
lib/base/size_hint.py
lib/meta/__init__.py
lib/meta/array.py
lib/meta/list.py
lib/meta/mapping.py
lib/types/__init__.py
lib/types/bitfield.py
lib/types/byte.py
lib/types/char.py
lib/types/dword.py
lib/types/float.py
lib/types/oword.py
lib/types/qword.py
lib/types/string.py
lib/types/structure.py
lib/types/union.py
lib/types/wchar.py
lib/types/word.py
paranoia.egg-info/PKG-INFO
paranoia.egg-info/SOURCES.txt
paranoia.egg-info/dependency_links.txt
paranoia.egg-info/top_level.txt