Metadata-Version: 1.1
Name: paranoia
Version: 0.7.0
Summary: A data structure library.
Home-page: https://github.com/frank2/paranoia
Author: frank2
Author-email: frank2@dc949.org
License: GPLv3
Keywords: data_structures ctypes
Platform: UNKNOWN
Classifier: Development Status :: 4 - Beta
Classifier: Topic :: Software Development :: Libraries
Classifier: License :: OSI Approved :: GNU General Public License v3 (GPLv3)
